topsis_main/topsis.py
topsis_101753002_Ashish-1.0.dist-info/LICENSE
topsis_101753002_Ashish-1.0.dist-info/METADATA
topsis_101753002_Ashish-1.0.dist-info/WHEEL
topsis_101753002_Ashish-1.0.dist-info/entry_points.txt
topsis_101753002_Ashish-1.0.dist-info/top_level.txt
topsis_101753002_Ashish-1.0.dist-info/RECORD
